[
    {
        "habit": "Sleep",
        "duration": "8hrs",
        "emotion": "Relax",
        "date": "2025-09-04 20:56:27"
    },
    {
        "habit": "Study",
        "duration": "2hrs",
        "emotion": "Happy",
        "date": "2025-09-04 20:56:38"
    },
    {
        "habit": "Playing",
        "duration": "3hrs",
        "emotion": "Joy",
        "date": "2025-09-04 20:56:48"
    },
    {
        "habit": "Read",
        "duration": "2hrs",
        "emotion": "Tired",
        "date": "2025-10-19 20:47:35"
    },
    {
        "habit": "Chatting",
        "duration": "1hrs",
        "emotion": "Happy",
        "date": "2025-10-20 23:33:43"
    }
]